Metadata-Version: 2.1
Name: io.github.mcarlos101.file-renamer
Version: 1.1.6
Summary: Rename files using a GUI desktop app for Linux & Windows
Author: Carlos
License: GNU GENERAL PUBLIC LICENSE
Project-URL: Homepage, https://github.com/mcarlos101/file-renamer
Project-URL: Repository, https://github.com/mcarlos101/file-renamer.git
Keywords: app,gui,rename,rename-files,batch-rename-files,renamer,linux-desktop,ubuntu,fedora,windows-desktop,macos-desktop,pyside6,qt-creator
Classifier: Development Status :: 5 - Production/Stable
Classifier: License :: OSI Approved :: GNU General Public License v3 or later (GPLv3+)
Classifier: Intended Audience :: End Users/Desktop
Classifier: Topic :: Utilities
Classifier: Programming Language :: Python
Classifier: Operating System :: POSIX :: Linux
Classifier: Topic :: Desktop Environment :: Gnome
Classifier: Topic :: Desktop Environment :: K Desktop Environment (KDE)
Classifier: Operating System :: Microsoft :: Windows :: Windows 11
Requires-Python: >=3.11
License-File: LICENSE
Requires-Dist: Unidecode
